.gitignore
CHANGES
LICENSE.md
MANIFEST.in
Makefile
README-CONDOR.md
README.md
VERSION
bigjob.conf
bigjob.sublime-project
bigjob_agent.conf
setup.cfg
setup.py
BigJob.egg-info/PKG-INFO
BigJob.egg-info/SOURCES.txt
BigJob.egg-info/dependency_links.txt
BigJob.egg-info/entry_points.txt
BigJob.egg-info/requires.txt
BigJob.egg-info/top_level.txt
api/__init__.py
api/base.py
bigjob/__init__.py
bigjob/bigjob_agent.py
bigjob/bigjob_agent_condor.py
bigjob/bigjob_manager.py
bigjob/state.py
bigjob/job_plugin/__init__.py
bigjob/job_plugin/ec2ssh.py
bigjob/job_plugin/gcessh.py
bigjob/job_plugin/slurmssh.py
bigjob/job_plugin/mesos/README.md
bigjob_dynamic/__init__.py
bigjob_dynamic/many_job.py
bigjob_dynamic/many_job_affinity.py
bootstrap/__init__.py
bootstrap/after_install.py
bootstrap/bigjob-bootstrap.py
bootstrap/bigjob-bootstrap.sh
bootstrap/generate_bigjob_bootstrap_script.py
cli/__init__.py
cli/pilot_cli.py
coordination/README.md
coordination/__init__.py
coordination/bigjob_coordination_advert.py
coordination/bigjob_coordination_redis.py
coordination/bigjob_coordination_zmq.py
doc/epydoc.bj.cfg
doc/epydoc.css
doc/generate-doc.sh
doc/html/api-objects.txt
doc/html/class-tree.html
doc/html/crarr.png
doc/html/epydoc-log.html
doc/html/epydoc.css
doc/html/epydoc.js
doc/html/help.html
doc/html/identifier-index.html
doc/html/index.html
doc/html/module-tree.html
doc/html/pilot-module.html
doc/html/pilot-pysrc.html
doc/html/pilot.api-module.html
doc/html/pilot.api-pysrc.html
doc/html/pilot.api.api-module.html
doc/html/pilot.api.api-pysrc.html
doc/html/pilot.api.api.ComputeDataService-class.html
doc/html/pilot.api.api.PilotError-class.html
doc/html/pilot.api.compute-module.html
doc/html/pilot.api.compute-pysrc.html
doc/html/pilot.api.compute.api-module.html
doc/html/pilot.api.compute.api-pysrc.html
doc/html/pilot.api.compute.api.Callback-class.html
doc/html/pilot.api.compute.api.ComputeUnit-class.html
doc/html/pilot.api.compute.api.ComputeUnitDescription-class.html
doc/html/pilot.api.compute.api.ComputeUnitService-class.html
doc/html/pilot.api.compute.api.PilotCompute-class.html
doc/html/pilot.api.compute.api.PilotComputeDescription-class.html
